ty-0.0.12.data/scripts/ty
ty-0.0.12.dist-info/METADATA
ty-0.0.12.dist-info/WHEEL
ty-0.0.12.dist-info/licenses/LICENSE
ty/__init__.py
ty/__main__.py
ty/py.typed
ty-0.0.12.dist-info/RECORD
