Metadata-Version: 2.4
Name: ty
Version: 0.0.12
Classifier: Development Status :: 4 - Beta
Classifier: Environment :: Console
Classifier: Intended Audience :: Developers
Classifier: Operating System :: OS Independent
Classifier: License :: OSI Approved :: MIT License
Classifier: Programming Language :: Python
Classifier: Programming Language :: Python :: 3.8
Classifier: Programming Language :: Python :: 3.9
Classifier: Programming Language :: Python :: 3.10
Classifier: Programming Language :: Python :: 3.11
Classifier: Programming Language :: Python :: 3.12
Classifier: Programming Language :: Python :: 3.13
Classifier: Programming Language :: Python :: 3.14
Classifier: Programming Language :: Python :: 3 :: Only
Classifier: Programming Language :: Rust
Classifier: Topic :: Software Development :: Quality Assurance
Classifier: Topic :: Software Development :: Testing
Classifier: Topic :: Software Development :: Libraries
Classifier: Topic :: Software Development :: Libraries :: Python Modules
License-File: LICENSE
Summary: An extremely fast Python type checker, written in Rust.
Keywords: ty,typing,analysis,check
Home-Page: https://github.com/astral-sh/ty/
Author-email: "Astral Software Inc." <hey@astral.sh>
Requires-Python: >=3.8
Project-URL: Repository, https://github.com/astral-sh/ty
Project-URL: Changelog, https://github.com/astral-sh/ty/blob/main/CHANGELOG.md
Project-URL: Releases, https://github.com/astral-sh/ty/releases
Project-URL: Discord, https://discord.gg/astral-sh
